feishu/Application.py
feishu/Decorator.py
feishu/FeishuException.py
feishu/Logs.py
feishu/Utils.py
feishu/__init__.py
feishu_sdk-1.0.3.dist-info/LICENSE
feishu_sdk-1.0.3.dist-info/METADATA
feishu_sdk-1.0.3.dist-info/WHEEL
feishu_sdk-1.0.3.dist-info/top_level.txt
feishu_sdk-1.0.3.dist-info/RECORD
