Metadata-Version: 2.1
Name: feishu-sdk
Version: 1.0.3
Summary: Feishu Third-party Libraries
Home-page: https://github.com/liyao2598330/feishu-sdk
Author: liyao
Author-email: liyao2598330@126.com
License: UNKNOWN
Platform: UNKNOWN
Classifier: Programming Language :: Python :: 2.7
Classifier: Programming Language :: Python :: 3
Classifier: License :: OSI Approved :: MIT License
Requires-Python: >=2.7
Requires-Dist: urllib3
Requires-Dist: requests
